kivymd_extensions/__init__.py
kivymd_extensions/sweetalert/__init__.py
kivymd_extensions/sweetalert/sweetalert.py
kivymd_extensions/sweetalert/animation/__init__.py
kivymd_extensions/sweetalert/animation/failure_icon.py
kivymd_extensions/sweetalert/animation/others_icon.py
kivymd_extensions/sweetalert/animation/success_icon.py
kivymd_extensions.sweetalert-0.1.5.dist-info/LICENSE
kivymd_extensions.sweetalert-0.1.5.dist-info/METADATA
kivymd_extensions.sweetalert-0.1.5.dist-info/WHEEL
kivymd_extensions.sweetalert-0.1.5.dist-info/top_level.txt
kivymd_extensions.sweetalert-0.1.5.dist-info/RECORD
