Metadata-Version: 2.1
Name: kivymd_extensions.sweetalert
Version: 0.1.5
Summary: Beautiful, responsive, customizable and accessible popup replacement
Home-page: https://github.com/kivymd-extensions/sweetalert
Author: KivyMD Team and other contributors
Author-email: kivydevelopment@gmail.com
License: MIT
Project-URL: Tracker, https://github.com/kivymd-extensions/sweetalert/issues
Keywords: kivymd_extensions,kivymd,kivy,material,ui
Platform: any
Classifier: Development Status :: 3 - Alpha
Classifier: License :: OSI Approved :: MIT License
Classifier: Programming Language :: Python :: 3 :: Only
Classifier: Programming Language :: Python :: 3
Classifier: Programming Language :: Python :: 3.6
Classifier: Programming Language :: Python :: 3.7
Classifier: Programming Language :: Python :: 3.8
Classifier: Programming Language :: Python :: 3.9
Classifier: Operating System :: OS Independent
Classifier: Operating System :: Android
Classifier: Operating System :: POSIX :: Linux
Classifier: Operating System :: POSIX :: BSD :: FreeBSD
Classifier: Operating System :: Microsoft :: Windows
Classifier: Operating System :: iOS
Classifier: Operating System :: MacOS
Classifier: Operating System :: MacOS :: MacOS X
Classifier: Environment :: MacOS X
Classifier: Environment :: Win32 (MS Windows)
Classifier: Environment :: X11 Applications
Classifier: Intended Audience :: Developers
Classifier: Intended Audience :: End Users/Desktop
Classifier: Intended Audience :: Information Technology
Classifier: Intended Audience :: Science/Research
Classifier: Topic :: Software Development :: User Interfaces
Classifier: Topic :: Scientific/Engineering :: Human Machine Interfaces
Classifier: Topic :: Scientific/Engineering :: Visualization
Requires-Python: >=3.6
Provides-Extra: dev
Provides-Extra: docs
